telstracalltocsv/__main__.py
telstracalltocsv-2.0.1.dist-info/METADATA
telstracalltocsv-2.0.1.dist-info/WHEEL
telstracalltocsv-2.0.1.dist-info/licenses/COPYING.md
telstracalltocsv-2.0.1.dist-info/RECORD
