Metadata-Version: 2.3
Name: telstracalltocsv
Version: 2.0.1
Summary: TelstraCallToCSV exports Telstra prepaid call logs to CSV files.
Project-URL: Homepage, https://github.com/Capta1nT0ad/TelstraCallToCSV
Project-URL: Issues, https://github.com/Capta1nT0ad/TelstraCallToCSV/issues
Author: Capta1nT0ad
License-File: COPYING.md
Classifier: License :: OSI Approved :: GNU General Public License v3 or later (GPLv3+)
Classifier: Operating System :: OS Independent
Classifier: Programming Language :: Python :: 3
Requires-Python: >=3.8
Requires-Dist: colorama
Requires-Dist: python-dateutil
Requires-Dist: requests
